bingx_api/__init__.py
bingx_api/api_config.py
bingx_api/future/__init__.py
bingx_api/future/rest/__init__.py
bingx_api/future/rest/core.py
bingx_api/future/rest/create_order.py
bingx_api/future/rest/create_order_list.py
bingx_api/future/rest/delete_all_order.py
bingx_api/future/rest/delete_order.py
bingx_api/future/rest/delete_order_list.py
bingx_api/future/rest/read_commission_rate.py
bingx_api/future/rest/read_contract_list.py
bingx_api/future/rest/read_funding_rate.py
bingx_api/future/rest/read_kline.py
bingx_api/future/rest/read_last_price.py
bingx_api/future/rest/read_leverage.py
bingx_api/future/rest/read_margin_tiered.py
bingx_api/future/rest/read_open_order_list.py
bingx_api/future/rest/read_order.py
bingx_api/future/rest/read_order_list.py
bingx_api/future/rest/read_position_list.py
bingx_api/future/rest/update_position_margin.py
bingx_api/future/rest/url.py
bingx_api/future/ws/delete_listen_key.py
bingx_api/future/ws/model/__init__.py
bingx_api/future/ws/model/base_streamer.py
bingx_api/future/ws/model/last_mark_price.py
bingx_api/future/ws/model/query_channel.py
bingx_api/future/ws/read_listen_key.py
bingx_api/future/ws/stream_account.py
bingx_api/future/ws/stream_channel.py
bingx_api/future/ws/stream_last_price.py
bingx_api/future/ws/update_listen_key.py
bingx_api/future/ws/url.py
bingx_api/future/ws/valid_listen_key.py
bingx_api/spot/__init__.py
bingx_api/spot/rest/__init__.py
bingx_api/spot/rest/core.py
bingx_api/spot/rest/create_order.py
bingx_api/spot/rest/create_order_list.py
bingx_api/spot/rest/delete_order_list.py
bingx_api/spot/rest/read_contract_list.py
bingx_api/spot/rest/read_kline.py
bingx_api/spot/rest/read_open_order_list.py
bingx_api/spot/rest/read_order.py
bingx_api/spot/rest/read_order_list.py
bingx_api/spot/rest/url.py
bingx_api/spot/ws/__init__.py
bingx_api/spot/ws/model/__init__.py
bingx_api/spot/ws/model/base_streamer.py
bingx_api/spot/ws/model/query_channel.py
bingx_api/spot/ws/stream_account.py
bingx_api/spot/ws/stream_channel.py
bingx_api-0.1.0.dist-info/LICENSE
bingx_api-0.1.0.dist-info/METADATA
bingx_api-0.1.0.dist-info/WHEEL
bingx_api-0.1.0.dist-info/RECORD
