Metadata-Version: 2.1
Name: bingx-api
Version: 0.1.0
Summary: This is yet another library to access Bingx's API.
License: BSD-3-Clause
Author: Chavithra PARANA
Author-email: chavithra@gmail.com
Requires-Python: >=3.12,<4.0
Classifier: License :: OSI Approved :: BSD License
Classifier: Operating System :: OS Independent
Classifier: Programming Language :: Python :: 3
Classifier: Programming Language :: Python :: 3.12
Requires-Dist: black (>=24.4.2,<25.0.0)
Requires-Dist: flake8 (>=7.0.0,<8.0.0)
Requires-Dist: mypy (>=1.10.0,<2.0.0)
Requires-Dist: types-requests (>=2.32.0.20240521,<3.0.0.0)
